pptxtopdf/__init__.py
pptxtopdf/__main__.py
pptxtopdf-0.0.2.dist-info/LICENSE
pptxtopdf-0.0.2.dist-info/METADATA
pptxtopdf-0.0.2.dist-info/WHEEL
pptxtopdf-0.0.2.dist-info/entry_points.txt
pptxtopdf-0.0.2.dist-info/top_level.txt
pptxtopdf-0.0.2.dist-info/RECORD
