Metadata-Version: 2.1
Name: pptxtopdf
Version: 0.0.2
Summary: Convert PowerPoint files to PDF
Home-page: https://github.com/hlviones/pptxtopdf
Author: Victor Ionescu
Author-email: hlviones@liverpool.ac.uk
Classifier: License :: OSI Approved :: MIT License
Classifier: Programming Language :: Python
Classifier: Programming Language :: Python :: 3
Classifier: Programming Language :: Python :: 3.6
Classifier: Programming Language :: Python :: 3.7
Classifier: Programming Language :: Python :: 3.8
Classifier: Programming Language :: Python :: 3.9
Classifier: Programming Language :: Python :: 3.10
Classifier: Programming Language :: Python :: 3.11
License-File: LICENSE
Requires-Dist: comtypes
